xaosim/DM.py
xaosim/QtMain.py
xaosim/__init__.py
xaosim/atmosphere.py
xaosim/camera.py
xaosim/instrument.py
xaosim/pupil.py
xaosim/scexao_shmlib.py
xaosim/sft.py
xaosim/shmlib.py
xaosim/wavefront.py
xaosim/zernike.py
xaosim-1.0.11.dist-info/METADATA
xaosim-1.0.11.dist-info/WHEEL
xaosim-1.0.11.dist-info/licenses/LICENSE.txt
xaosim-1.0.11.dist-info/RECORD
